phase_space_2d/__init__.py
phase_space_2d/phase_space.py
phase_space_2d-0.1.0.dist-info/METADATA
phase_space_2d-0.1.0.dist-info/WHEEL
phase_space_2d-0.1.0.dist-info/top_level.txt
phase_space_2d-0.1.0.dist-info/RECORD
